soam/__init__.py
soam/alembic.ini
soam/cfg.py
soam/constants.py
soam/data_models.py
soam/core/__init__.py
soam/core/runner.py
soam/core/step.py
soam/db_migrations/README
soam/db_migrations/env.py
soam/db_migrations/script.py.mako
soam/db_migrations/versions/74f172dd880e_first.py
soam/models/__init__.py
soam/models/base.py
soam/models/exponential.py
soam/models/orbit.py
soam/models/prophet.py
soam/models/sarimax.py
soam/plotting/__init__.py
soam/plotting/forecast_plotter.py
soam/plotting/plot_utils.py
soam/reporting/__init__.py
soam/reporting/gsheets_report.py
soam/reporting/mail_report.py
soam/reporting/pdf_report.py
soam/reporting/slack_report.py
soam/resources/mail_report.html
soam/resources/pdf_report.tpl
soam/savers/__init__.py
soam/savers/csv_saver.py
soam/savers/db_saver.py
soam/savers/savers.py
soam/utilities/__init__.py
soam/utilities/helpers.py
soam/utilities/utils.py
soam/workflow/__init__.py
soam/workflow/anomalies.py
soam/workflow/backtester.py
soam/workflow/forecaster.py
soam/workflow/merge_concat.py
soam/workflow/slicer.py
soam/workflow/store.py
soam/workflow/time_series_extractor.py
soam/workflow/transformer.py
tests/__init__.py
tests/db_test_case.py
tests/helpers.py
tests/integration/__init__.py
tests/integration/test_integration.py
tests/mlflow/__init__.py
tests/mlflow/test_mlflow_logging.py
tests/models/__init__.py
tests/models/test_exponential.py
tests/models/test_orbit.py
tests/models/test_sarimax.py
tests/plotting/__init__.py
tests/plotting/test_forecast_plotter.py
tests/plotting/baseline/test_ForecastPlotterTask_overlapping.png
tests/plotting/baseline/test_ForecastPlotterTask_simple.png
tests/reporting/test_gsheets_report.py
tests/reporting/test_pdf_report.py
tests/reporting/test_slack_report.py
tests/utilities/__init__.py
tests/utilities/test_utils.py
tests/utilities/resources/test_utils/initial_dataframe.csv
tests/utilities/resources/test_utils/all_default/train_0.csv
tests/utilities/resources/test_utils/all_default/train_1.csv
soam-0.10.2.dist-info/LICENCE
soam-0.10.2.dist-info/METADATA
soam-0.10.2.dist-info/WHEEL
soam-0.10.2.dist-info/top_level.txt
soam-0.10.2.dist-info/RECORD
