Metadata-Version: 2.1
Name: soam
Version: 0.10.2
Summary: Tools for time series analysis, plotting and reporting.
Home-page: UNKNOWN
Author: Mutt Data
Author-email: info@muttdata.ai
License: UNKNOWN
Keywords: anomalies forecasting reporting
Platform: UNKNOWN
Classifier: Programming Language :: Python :: 3
Classifier: License :: OSI Approved :: Apache Software License
Classifier: Operating System :: OS Independent
Requires-Python: ~=3.6
License-File: LICENCE
Requires-Dist: jinja2
Requires-Dist: pandas (<1.3.0,>=1.0.0)
Requires-Dist: Cython (<0.29.18,>=0.29)
Requires-Dist: sqlalchemy (<1.4.0,>=1.3.0)
Requires-Dist: sqlalchemy-utils
Requires-Dist: alembic
Requires-Dist: python-decouple
Requires-Dist: prefect (==0.15.13)
Requires-Dist: filelock
Requires-Dist: wheel
Requires-Dist: muttlib (<2,>=1.4.19)
Requires-Dist: numpy (<2,>=1.20)
Requires-Dist: matplotlib
Provides-Extra: all
Requires-Dist: flake8-bugbear ; extra == 'all'
Requires-Dist: flake8-docstrings ; extra == 'all'
Requires-Dist: bump2version ; extra == 'all'
Requires-Dist: docutils (<0.17,>=0.12) ; extra == 'all'
Requires-Dist: sphinx ; extra == 'all'
Requires-Dist: sphinxcontrib.mermaid ; extra == 'all'
Requires-Dist: sphinx-rtd-theme ; extra == 'all'
Requires-Dist: m2r2 (>=0.3.0) ; extra == 'all'
Requires-Dist: pre-commit (==2.5.0) ; extra == 'all'
Requires-Dist: isort (==4.3.21) ; extra == 'all'
Requires-Dist: black (==19.10b0) ; extra == 'all'
Requires-Dist: mypy (==0.782) ; extra == 'all'
Requires-Dist: pylint (==2.4.4) ; extra == 'all'
Requires-Dist: nox ; extra == 'all'
Requires-Dist: interrogate ; extra == 'all'
Requires-Dist: pytest ; extra == 'all'
Requires-Dist: pytest-mpl ; extra == 'all'
Requires-Dist: pytest-xdist ; extra == 'all'
Requires-Dist: pytest-cov ; extra == 'all'
Requires-Dist: pytest-html ; extra == 'all'
Requires-Dist: pytest-mock ; extra == 'all'
Requires-Dist: hypothesis ; extra == 'all'
Requires-Dist: psycopg2-binary ; extra == 'all'
Requires-Dist: nbval ; extra == 'all'
Requires-Dist: pdftotext (==2.1.5) ; extra == 'all'
Requires-Dist: slackclient (>=2.0.0) ; extra == 'all'
Requires-Dist: orbit-ml (==1.0.13) ; extra == 'all'
Requires-Dist: pystan (==2.19.1.1) ; extra == 'all'
Requires-Dist: prophet (==1.1.1) ; extra == 'all'
Requires-Dist: holidays (==0.24) ; extra == 'all'
Requires-Dist: jupytext (==1.10.2) ; extra == 'all'
Requires-Dist: papermill (==2.3.2) ; extra == 'all'
Requires-Dist: nbconvert (==5.6) ; extra == 'all'
Requires-Dist: gspread-pandas ; extra == 'all'
Requires-Dist: muttlib[gsheets] (<2,>=1.0) ; extra == 'all'
Requires-Dist: statsmodels (<0.12,>=0.11) ; extra == 'all'
Requires-Dist: mlflow (==1.17.0) ; extra == 'all'
Provides-Extra: dev
Requires-Dist: flake8-bugbear ; extra == 'dev'
Requires-Dist: flake8-docstrings ; extra == 'dev'
Requires-Dist: bump2version ; extra == 'dev'
Requires-Dist: docutils (<0.17,>=0.12) ; extra == 'dev'
Requires-Dist: sphinx ; extra == 'dev'
Requires-Dist: sphinxcontrib.mermaid ; extra == 'dev'
Requires-Dist: sphinx-rtd-theme ; extra == 'dev'
Requires-Dist: m2r2 (>=0.3.0) ; extra == 'dev'
Requires-Dist: pre-commit (==2.5.0) ; extra == 'dev'
Requires-Dist: isort (==4.3.21) ; extra == 'dev'
Requires-Dist: black (==19.10b0) ; extra == 'dev'
Requires-Dist: mypy (==0.782) ; extra == 'dev'
Requires-Dist: pylint (==2.4.4) ; extra == 'dev'
Requires-Dist: nox ; extra == 'dev'
Provides-Extra: gsheets_report
Requires-Dist: gspread-pandas ; extra == 'gsheets_report'
Requires-Dist: muttlib[gsheets] (<2,>=1.0) ; extra == 'gsheets_report'
Provides-Extra: mlflow
Requires-Dist: mlflow (==1.17.0) ; extra == 'mlflow'
Provides-Extra: orbit
Requires-Dist: orbit-ml (==1.0.13) ; extra == 'orbit'
Provides-Extra: pdf_report
Requires-Dist: jupytext (==1.10.2) ; extra == 'pdf_report'
Requires-Dist: papermill (==2.3.2) ; extra == 'pdf_report'
Requires-Dist: nbconvert (==5.6) ; extra == 'pdf_report'
Provides-Extra: prophet
Requires-Dist: pystan (==2.19.1.1) ; extra == 'prophet'
Requires-Dist: prophet (==1.1.1) ; extra == 'prophet'
Requires-Dist: holidays (==0.24) ; extra == 'prophet'
Provides-Extra: report
Requires-Dist: slackclient (>=2.0.0) ; extra == 'report'
Requires-Dist: jupytext (==1.10.2) ; extra == 'report'
Requires-Dist: papermill (==2.3.2) ; extra == 'report'
Requires-Dist: nbconvert (==5.6) ; extra == 'report'
Requires-Dist: gspread-pandas ; extra == 'report'
Requires-Dist: muttlib[gsheets] (<2,>=1.0) ; extra == 'report'
Provides-Extra: slack
Requires-Dist: slackclient (>=2.0.0) ; extra == 'slack'
Provides-Extra: statsmodels
Requires-Dist: statsmodels (<0.12,>=0.11) ; extra == 'statsmodels'
Provides-Extra: test
Requires-Dist: interrogate ; extra == 'test'
Requires-Dist: nox ; extra == 'test'
Requires-Dist: pytest ; extra == 'test'
Requires-Dist: pytest-mpl ; extra == 'test'
Requires-Dist: pytest-xdist ; extra == 'test'
Requires-Dist: pytest-cov ; extra == 'test'
Requires-Dist: pytest-html ; extra == 'test'
Requires-Dist: pytest-mock ; extra == 'test'
Requires-Dist: hypothesis ; extra == 'test'
Requires-Dist: psycopg2-binary ; extra == 'test'
Requires-Dist: nbval ; extra == 'test'
Requires-Dist: pdftotext (==2.1.5) ; extra == 'test'
